pydlmeta/__init__.py
pydlmeta/config.py
pydlmeta/dtype_map.py
pydlmeta/meta.py
pydlmeta/utils.py
pydlmeta/identifier/__init__.py
pydlmeta/identifier/dataset.py
pydlmeta/identifier/model.py
pydlmeta/identifier/types.py
pydlmeta-1.0.3.dist-info/METADATA
pydlmeta-1.0.3.dist-info/WHEEL
pydlmeta-1.0.3.dist-info/dependency_links.txt
pydlmeta-1.0.3.dist-info/top_level.txt
pydlmeta-1.0.3.dist-info/RECORD
