Metadata-Version: 2.1
Name: pydlmeta
Version: 1.0.3
Summary: UNKNOWN
Home-page: UNKNOWN
License: Apache License 2.0
Platform: UNKNOWN
Requires-Dist: tensorflow
Requires-Dist: tflite
Requires-Dist: keras
Requires-Dist: torch
Requires-Dist: torchvision
Requires-Dist: numpy
Requires-Dist: onnx
Requires-Dist: loguru
Requires-Dist: openvino
Requires-Dist: onnx2torch
